wtrwrks/__init__.py
wtrwrks/read_write/__init__.py
wtrwrks/read_write/tf_features.py
wtrwrks/string_manipulations/__init__.py
wtrwrks/string_manipulations/diff.py
wtrwrks/string_manipulations/ja_stopwords.py
wtrwrks/string_manipulations/ko_stopwords.py
wtrwrks/string_manipulations/zh_hans_stopwords.py
wtrwrks/string_manipulations/unit_test/__init__.py
wtrwrks/string_manipulations/unit_test/test_diff.py
wtrwrks/tanks/__init__.py
wtrwrks/tanks/add.py
wtrwrks/tanks/bert_random_insert.py
wtrwrks/tanks/bool.py
wtrwrks/tanks/cast.py
wtrwrks/tanks/cat_to_index.py
wtrwrks/tanks/clone.py
wtrwrks/tanks/concatenate.py
wtrwrks/tanks/datetime_to_num.py
wtrwrks/tanks/dim_size.py
wtrwrks/tanks/div.py
wtrwrks/tanks/effective_length.py
wtrwrks/tanks/flat_tokenize.py
wtrwrks/tanks/flatten.py
wtrwrks/tanks/getitem.py
wtrwrks/tanks/half_width.py
wtrwrks/tanks/iterate.py
wtrwrks/tanks/lemmatize.py
wtrwrks/tanks/lower_case.py
wtrwrks/tanks/mul.py
wtrwrks/tanks/one_hot.py
wtrwrks/tanks/pack.py
wtrwrks/tanks/pack_with_row_map.py
wtrwrks/tanks/partition.py
wtrwrks/tanks/print_val.py
wtrwrks/tanks/random_choice.py
wtrwrks/tanks/random_replace.py
wtrwrks/tanks/reduce.py
wtrwrks/tanks/remove.py
wtrwrks/tanks/replace.py
wtrwrks/tanks/replace_substring.py
wtrwrks/tanks/reshape.py
wtrwrks/tanks/shape.py
wtrwrks/tanks/split.py
wtrwrks/tanks/sub.py
wtrwrks/tanks/tank_defs.py
wtrwrks/tanks/tile.py
wtrwrks/tanks/tokenize.py
wtrwrks/tanks/transpose.py
wtrwrks/tanks/tube_iterables.py
wtrwrks/tanks/utils.py
wtrwrks/tanks/unit_test/__init__.py
wtrwrks/tanks/unit_test/test_add.py
wtrwrks/tanks/unit_test/test_bert_random_insert.py
wtrwrks/tanks/unit_test/test_bool.py
wtrwrks/tanks/unit_test/test_cast.py
wtrwrks/tanks/unit_test/test_cat_to_index.py
wtrwrks/tanks/unit_test/test_concatenate.py
wtrwrks/tanks/unit_test/test_datetime_to_num.py
wtrwrks/tanks/unit_test/test_div.py
wtrwrks/tanks/unit_test/test_half_width.py
wtrwrks/tanks/unit_test/test_iterate.py
wtrwrks/tanks/unit_test/test_lemmatize.py
wtrwrks-2.0.5.dist-info/LICENSE
wtrwrks-2.0.5.dist-info/METADATA
wtrwrks-2.0.5.dist-info/WHEEL
wtrwrks-2.0.5.dist-info/top_level.txt
wtrwrks-2.0.5.dist-info/RECORD
