Metadata-Version: 2.1
Name: wtrwrks
Version: 2.0.5
Summary: A system for creating reversible data transformations
Home-page: UNKNOWN
Author: Christopher Silkworth
Author-email: crsilkworth@gmail.com
License: UNKNOWN
Platform: UNKNOWN
Requires-Dist: numpy (~=1.14)
Requires-Dist: pandas (~=0.23)
Requires-Dist: matplotlib (~=2.2)
Requires-Dist: scipy (~=1.1)
Requires-Dist: mpu (~=0.14)
Requires-Dist: tables (~=3.4)
Requires-Dist: tensorflow (~=1.14)
Requires-Dist: nltk (~=3.4)
Requires-Dist: tinysegmenter (~=0.4)
Requires-Dist: chop (~=1.0)
Requires-Dist: konlpy (~=0.5)
Requires-Dist: simplejson (~=3.16)
Requires-Dist: gensim (~=3.6)
Requires-Dist: dill (~=0.3)
Requires-Dist: sqlalchemy (~=1.3)
Requires-Dist: pathos (~=0.2)
